prometheux_chain/__init__.py
prometheux_chain/config.py
prometheux_chain/config.yaml
prometheux_chain/client/__init__.py
prometheux_chain/client/jarvispy_client.py
prometheux_chain/common/__init__.py
prometheux_chain/common/vadalog_utils.py
prometheux_chain/concept/__init__.py
prometheux_chain/concept/manage_concepts.py
prometheux_chain/data/__init__.py
prometheux_chain/data/database.py
prometheux_chain/data/manage_data.py
prometheux_chain/kg/__init__.py
prometheux_chain/kg/manage_kgs.py
prometheux_chain/project/__init__.py
prometheux_chain/project/manage_projects.py
prometheux_chain/user/__init__.py
prometheux_chain/user/manage_users.py
prometheux_chain/workspace/__init__.py
prometheux_chain-0.2.13.dist-info/licenses/LICENSE
prometheux_chain-0.2.13.dist-info/METADATA
prometheux_chain-0.2.13.dist-info/WHEEL
prometheux_chain-0.2.13.dist-info/top_level.txt
prometheux_chain-0.2.13.dist-info/RECORD
